projects/100-snps/fine_tune_no_pretrain_only_100.cfg
projects/100-snps/fine_tune_no_pretrain_only_100_learned_pos_encoding.cfg
projects/100-snps/fine_tune_no_pretrain_only_100_learned_pos_encoding_non_sparse.cfg
projects/100-snps/fine_tune_no_pretrain_only_41_learned_pos_encoding_big_batch.cfg
projects/100-snps/fine_tune_no_pretrain_only_41_learned_pos_encoding_big_batch_alpha_0.1.cfg
projects/100-snps/fine_tune_no_pretrain_only_41_learned_pos_encoding_big_batch_alpha_0.3.cfg
projects/100-snps/fine_tune_no_pretrain_only_41_learned_pos_encoding_big_batch_alpha_0.7.cfg
projects/100-snps/fine_tune_no_pretrain_only_41_learned_pos_encoding_big_batch_alpha_0.cfg
projects/100-snps/fine_tune_no_pretrain_only_41_learned_pos_encoding_non_sparse_big_batch.cfg
projects/100-snps/fine_tune_no_pretrain_only_499_learned_pos_encoding_big_batch.cfg
projects/100-snps/fine_tune_no_pretrain_only_499_learned_pos_encoding_non_sparse_big_batch.cfg
projects/100-snps/fine_tune_no_pretrain_only_511.cfg
projects/100-snps/fine_tune_no_pretrain_only_511_learned_big_batch.cfg
projects/100-snps/fine_tune_no_pretrain_only_511_learned_big_batch.py
projects/100-snps/fine_tune_no_pretrain_only_511_learned_big_batch_10k-warmup.cfg
projects/100-snps/fine_tune_no_pretrain_only_511_learned_big_batch_10k-warmup.py
projects/100-snps/fine_tune_no_pretrain_only_511_learned_big_batch_5k-warmup.cfg
projects/100-snps/fine_tune_no_pretrain_only_511_learned_big_batch_5k-warmup.py
projects/100-snps/fine_tune_no_pretrain_only_511_learned_pos_encoding.cfg
projects/100-snps/fine_tune_no_pretrain_only_511_learned_pos_encoding_big_batch.cfg
projects/100-snps/fine_tune_no_pretrain_only_511_learned_pos_encoding_non_sparse.cfg
projects/100-snps/train.py
projects/100-snps/train100.py
projects/100-snps/train100_with_non-sparse.py
projects/100-snps/train100_with_pos.py
projects/100-snps/train41_with_big-batch.py
projects/100-snps/train41_with_big-batch0.1.py
projects/100-snps/train41_with_big-batch0.3.py
snp_transformer-0.5.2.dist-info/LICENSE
snp_transformer-0.5.2.dist-info/METADATA
snp_transformer-0.5.2.dist-info/WHEEL
snp_transformer-0.5.2.dist-info/top_level.txt
snp_transformer-0.5.2.dist-info/RECORD
