Metadata-Version: 2.1
Name: snp-transformer
Version: 0.5.2
Summary: SNP Transformer
Author-email: Kenneth Enevoldsen <kennethcenevoldsen@gmail.com>
License: MIT License
Project-URL: homepage, https://github.com/KennethEnevoldsen/snp-transformer
Project-URL: repository, https://github.com/KennethEnevoldsen/snp-transformer
Project-URL: documentation, https://KennethEnevoldsen.github.io/snp-transformer/
Classifier: Operating System :: POSIX :: Linux
Classifier: Operating System :: MacOS :: MacOS X
Classifier: Programming Language :: Python :: 3.9
Classifier: Programming Language :: Python :: 3.10
Classifier: Programming Language :: Python :: 3.11
Requires-Python: >=3.9
License-File: LICENSE
Requires-Dist: pydantic >=2.1.1
Requires-Dist: torch ==2.2.1
Requires-Dist: confection >=0.1.1
Requires-Dist: pandas >=2.0.3
Requires-Dist: lightning >=2.0.9
Requires-Dist: wandb >=0.15.8
Requires-Dist: pyarrow >=12.0.0
Requires-Dist: polars >=0.19.3
Provides-Extra: dev
Requires-Dist: cruft >=2.0.0 ; extra == 'dev'
Requires-Dist: pyright >=1.1.344 ; extra == 'dev'
Requires-Dist: pyright-polite >=0.0.1 ; extra == 'dev'
Requires-Dist: pre-commit >=2.20.0 ; extra == 'dev'
Requires-Dist: ruff >=0.0.254 ; extra == 'dev'
Requires-Dist: black[jupyter] >=22.8.0 ; extra == 'dev'
Requires-Dist: invoke >=2.2.0 ; extra == 'dev'
Provides-Extra: docs
Requires-Dist: jupyter >=1.0.0 ; extra == 'docs'
Provides-Extra: tests
Requires-Dist: pytest >=7.1.3 ; extra == 'tests'
Requires-Dist: pytest-cov >=3.0.0 ; extra == 'tests'
Requires-Dist: pytest-xdist >=3.0.0 ; extra == 'tests'
Requires-Dist: pytest-sugar >=0.9.4 ; extra == 'tests'
Requires-Dist: tox >=4.5.0 ; extra == 'tests'
